karabo_services/__init__.py
karabo_services/entrypoints.py
karabo_services/containers/compose.yaml
karabo_services/containers/grafana_provisioning/influx.yaml
karabo_services/overwrites/karabo_dataLoggerManager.run
karabo_services/overwrites/karabo_projectDBServer.run
karabo_services/service.in/default/.svscan/run
karabo_services/service.in/default/karabo_configServer/down
karabo_services/service.in/default/karabo_configServer/name
karabo_services/service.in/default/karabo_configServer/run
karabo_services/service.in/default/karabo_configServer/log/run
karabo_services/service.in/default/karabo_daemonServer/down
karabo_services/service.in/default/karabo_daemonServer/name
karabo_services/service.in/default/karabo_daemonServer/run
karabo_services/service.in/default/karabo_daemonServer/log/run
karabo_services/service.in/default/karabo_dataLogger/down
karabo_services/service.in/default/karabo_dataLogger/name
karabo_services/service.in/default/karabo_dataLogger/run
karabo_services/service.in/default/karabo_dataLogger/log/run
karabo_services/service.in/default/karabo_dataLoggerManager/down
karabo_services/service.in/default/karabo_dataLoggerManager/name
karabo_services/service.in/default/karabo_dataLoggerManager/run
karabo_services/service.in/default/karabo_dataLoggerManager/log/run
karabo_services/service.in/default/karabo_guiServer/down
karabo_services/service.in/default/karabo_guiServer/name
karabo_services/service.in/default/karabo_guiServer/run
karabo_services/service.in/default/karabo_guiServer/log/run
karabo_services/service.in/default/karabo_macroServer/down
karabo_services/service.in/default/karabo_macroServer/name
karabo_services/service.in/default/karabo_macroServer/run
karabo_services/service.in/default/karabo_macroServer/log/run
karabo_services/service.in/default/karabo_projectDBServer/down
karabo_services/service.in/default/karabo_projectDBServer/name
karabo_services/service.in/default/karabo_projectDBServer/run
karabo_services-3.0.8.dist-info/licenses/LICENSE.md
karabo_services-3.0.8.dist-info/METADATA
karabo_services-3.0.8.dist-info/WHEEL
karabo_services-3.0.8.dist-info/entry_points.txt
karabo_services-3.0.8.dist-info/top_level.txt
karabo_services-3.0.8.dist-info/RECORD
