Metadata-Version: 2.4
Name: karabo.services
Version: 3.0.8
Summary: Services required to run Karabo
Author-email: European XFEL GmbH <opensource@xfel.eu>
Maintainer-email: "S. Hauf" <steffen.hauf@xfel.eu>, "D. Goeries" <dennis.goeries@xfel.eu>
License-Expression: MPL-2.0
Project-URL: Homepage, https://github.com/European-XFEL/Karabo
Project-URL: Bug Reports, https://github.com/European-XFEL/Karabo/issues
Project-URL: Source, https://github.com/European-XFEL/Karabo
Keywords: Karabo,SCADA,async,control system
Classifier: Development Status :: 5 - Production/Stable
Classifier: Intended Audience :: Developers
Classifier: Intended Audience :: Science/Research
Requires-Python: >=3.12
License-File: LICENSE.md
Requires-Dist: karabo.daemontools==3.0.8
Requires-Dist: karabo.karathon==3.0.8
Provides-Extra: with-cpp
Requires-Dist: karabo.cpp==3.0.8; extra == "with-cpp"
Dynamic: license-file
